config.py
cryptor.py
input.py
keys.py
output.py
password.py
pysafe.py
reset.py
pysafe-0.2.2.data/scripts/pysafe.py
pysafe-0.2.2.dist-info/LICENSE
pysafe-0.2.2.dist-info/METADATA
pysafe-0.2.2.dist-info/WHEEL
pysafe-0.2.2.dist-info/top_level.txt
pysafe-0.2.2.dist-info/RECORD
