Metadata-Version: 2.1
Name: pysafe
Version: 0.2.2
Summary: Python password manger
Home-page: https://github.com/MNKanout/Pysafe
Author: MNKANOUT
Author-email: mnkanout@gmail.com
License: UNKNOWN
Platform: UNKNOWN
Classifier: Programming Language :: Python :: 3
Classifier: License :: OSI Approved :: MIT License
Classifier: Operating System :: MacOS
Classifier: Operating System :: Microsoft :: Windows :: Windows 10
Classifier: Natural Language :: English
Requires-Python: >=3.7
Requires-Dist: cffi (==1.14.0)
Requires-Dist: colorama (==0.4.3)
Requires-Dist: cryptography (==2.8)
Requires-Dist: pycparser (==2.20)
Requires-Dist: six (==1.14.0)
